<?xml version="1.0" encoding="windows-1252"?>
<XMI xmi.version="1.1" xmlns:UML="omg.org/UML1.3">
	<XMI.header>
		<XMI.documentation>
			<XMI.exporter>Enterprise Architect</XMI.exporter>
			<XMI.exporterVersion>2.5</XMI.exporterVersion>
		</XMI.documentation>
	</XMI.header>
	<XMI.content>
		<UML:Model name="EA Model" xmi.id="MX_EAID_EEA186C1_50AD_43fe_84BC_7272F4234FCD">
			<UML:Namespace.ownedElement>
				<UML:Class name="EARootClass" xmi.id="EAID_11111111_5487_4080_A7F4_41526CB0AA00" isRoot="true" isLeaf="false" isAbstract="false"/>
				<UML:Package name="Dictamen" xmi.id="EAPK_EEA186C1_50AD_43fe_84BC_7272F4234FCD" isRoot="true" isLeaf="false" isAbstract="false" visibility="public">
					<UML:ModelElement.taggedValue>
						<UML:TaggedValue tag="created" value="2015-08-25 11:14:25"/>
						<UML:TaggedValue tag="modified" value="2015-08-19 16:18:37"/>
						<UML:TaggedValue tag="iscontrolled" value="TRUE"/>
						<UML:TaggedValue tag="xmlpath" value="Dictamen.xml"/>
						<UML:TaggedValue tag="lastloaddate" value="2015-08-28 12:30:05"/>
						<UML:TaggedValue tag="lastsavedate" value="2015-08-25 11:14:25"/>
						<UML:TaggedValue tag="isprotected" value="FALSE"/>
						<UML:TaggedValue tag="usedtd" value="FALSE"/>
						<UML:TaggedValue tag="logxml" value="FALSE"/>
						<UML:TaggedValue tag="packageFlags" value="isModel=1;VCCFG=Dictamen;CRC=0;"/>
						<UML:TaggedValue tag="batchsave" value="0"/>
						<UML:TaggedValue tag="batchload" value="0"/>
					</UML:ModelElement.taggedValue>
					<UML:Namespace.ownedElement>
						<UML:Collaboration xmi.id="EAID_EEA186C1_50AD_43fe_84BC_7272F4234FCD_Collaboration" name="Collaborations">
							<UML:Namespace.ownedElement>
								<UML:ClassifierRole name="04 Diseño Tecnico" xmi.id="EAID_18FE430E_5F97_4cf9_BDAD_279FA43C2A8B" visibility="public" base="EAID_11111111_5487_4080_A7F4_41526CB0AA00">
									<UML:ModelElement.taggedValue>
										<UML:TaggedValue tag="isAbstract" value="false"/>
										<UML:TaggedValue tag="isSpecification" value="false"/>
										<UML:TaggedValue tag="ea_stype" value="Package"/>
										<UML:TaggedValue tag="ea_ntype" value="0"/>
										<UML:TaggedValue tag="isActive" value="false"/>
										<UML:TaggedValue tag="package" value="EAPK_EEA186C1_50AD_43fe_84BC_7272F4234FCD"/>
										<UML:TaggedValue tag="date_created" value="2015-08-19 15:57:27"/>
										<UML:TaggedValue tag="date_modified" value="2015-08-19 16:03:28"/>
										<UML:TaggedValue tag="tagged" value="0"/>
										<UML:TaggedValue tag="package2" value="EAID_18FE430E_5F97_4cf9_BDAD_279FA43C2A8B"/>
										<UML:TaggedValue tag="package_name" value="Dictamen"/>
										<UML:TaggedValue tag="phase" value="1.0"/>
										<UML:TaggedValue tag="complexity" value="1"/>
										<UML:TaggedValue tag="status" value="Proposed"/>
										<UML:TaggedValue tag="tpos" value="7"/>
										<UML:TaggedValue tag="ea_localid" value="24"/>
										<UML:TaggedValue tag="ea_eleType" value="package"/>
										<UML:TaggedValue tag="style" value="BackColor=-1;BorderColor=-1;BorderWidth=-1;FontColor=-1;VSwimLanes=1;HSwimLanes=1;BorderStyle=0;"/>
									</UML:ModelElement.taggedValue>
								</UML:ClassifierRole>
								<UML:ClassifierRole name="02 Modelo Funcional" xmi.id="EAID_637A3138_D9F0_49ea_A177_EC26F6D73622" visibility="public" base="EAID_11111111_5487_4080_A7F4_41526CB0AA00">
									<UML:ModelElement.taggedValue>
										<UML:TaggedValue tag="isAbstract" value="false"/>
										<UML:TaggedValue tag="isSpecification" value="false"/>
										<UML:TaggedValue tag="ea_stype" value="Package"/>
										<UML:TaggedValue tag="ea_ntype" value="0"/>
										<UML:TaggedValue tag="isActive" value="false"/>
										<UML:TaggedValue tag="package" value="EAPK_EEA186C1_50AD_43fe_84BC_7272F4234FCD"/>
										<UML:TaggedValue tag="date_created" value="2015-08-19 15:57:05"/>
										<UML:TaggedValue tag="date_modified" value="2015-08-19 16:08:20"/>
										<UML:TaggedValue tag="tagged" value="0"/>
										<UML:TaggedValue tag="package2" value="EAID_637A3138_D9F0_49ea_A177_EC26F6D73622"/>
										<UML:TaggedValue tag="package_name" value="Dictamen"/>
										<UML:TaggedValue tag="phase" value="1.0"/>
										<UML:TaggedValue tag="complexity" value="1"/>
										<UML:TaggedValue tag="status" value="Proposed"/>
										<UML:TaggedValue tag="tpos" value="3"/>
										<UML:TaggedValue tag="ea_localid" value="22"/>
										<UML:TaggedValue tag="ea_eleType" value="package"/>
										<UML:TaggedValue tag="style" value="BackColor=-1;BorderColor=-1;BorderWidth=-1;FontColor=-1;VSwimLanes=1;HSwimLanes=1;BorderStyle=0;"/>
									</UML:ModelElement.taggedValue>
								</UML:ClassifierRole>
								<UML:ClassifierRole name="03 Modelo de Requerimientos" xmi.id="EAID_7774EFC6_D830_40a8_83A5_256C6BF2B95E" visibility="public" base="EAID_11111111_5487_4080_A7F4_41526CB0AA00">
									<UML:ModelElement.taggedValue>
										<UML:TaggedValue tag="isAbstract" value="false"/>
										<UML:TaggedValue tag="isSpecification" value="false"/>
										<UML:TaggedValue tag="ea_stype" value="Package"/>
										<UML:TaggedValue tag="ea_ntype" value="0"/>
										<UML:TaggedValue tag="isActive" value="false"/>
										<UML:TaggedValue tag="package" value="EAPK_EEA186C1_50AD_43fe_84BC_7272F4234FCD"/>
										<UML:TaggedValue tag="date_created" value="2015-08-19 16:05:20"/>
										<UML:TaggedValue tag="date_modified" value="2015-08-19 16:07:59"/>
										<UML:TaggedValue tag="tagged" value="0"/>
										<UML:TaggedValue tag="package2" value="EAID_7774EFC6_D830_40a8_83A5_256C6BF2B95E"/>
										<UML:TaggedValue tag="package_name" value="Dictamen"/>
										<UML:TaggedValue tag="phase" value="1.0"/>
										<UML:TaggedValue tag="complexity" value="1"/>
										<UML:TaggedValue tag="status" value="Proposed"/>
										<UML:TaggedValue tag="tpos" value="2"/>
										<UML:TaggedValue tag="ea_localid" value="21"/>
										<UML:TaggedValue tag="ea_eleType" value="package"/>
										<UML:TaggedValue tag="style" value="BackColor=-1;BorderColor=-1;BorderWidth=-1;FontColor=-1;VSwimLanes=1;HSwimLanes=1;BorderStyle=0;"/>
									</UML:ModelElement.taggedValue>
								</UML:ClassifierRole>
								<UML:ClassifierRole name="01 Modelo de Procesos" xmi.id="EAID_9D49D945_9AF5_4ecb_A561_AB014F6E260C" visibility="public" base="EAID_11111111_5487_4080_A7F4_41526CB0AA00">
									<UML:ModelElement.taggedValue>
										<UML:TaggedValue tag="isAbstract" value="false"/>
										<UML:TaggedValue tag="isSpecification" value="false"/>
										<UML:TaggedValue tag="ea_stype" value="Package"/>
										<UML:TaggedValue tag="ea_ntype" value="0"/>
										<UML:TaggedValue tag="version" value="1.0"/>
										<UML:TaggedValue tag="isActive" value="false"/>
										<UML:TaggedValue tag="package" value="EAPK_EEA186C1_50AD_43fe_84BC_7272F4234FCD"/>
										<UML:TaggedValue tag="date_created" value="2015-08-19 15:58:39"/>
										<UML:TaggedValue tag="date_modified" value="2015-08-19 16:03:02"/>
										<UML:TaggedValue tag="gentype" value="C#"/>
										<UML:TaggedValue tag="tagged" value="0"/>
										<UML:TaggedValue tag="package2" value="EAID_9D49D945_9AF5_4ecb_A561_AB014F6E260C"/>
										<UML:TaggedValue tag="package_name" value="Dictamen"/>
										<UML:TaggedValue tag="phase" value="1.0"/>
										<UML:TaggedValue tag="complexity" value="1"/>
										<UML:TaggedValue tag="status" value="Proposed"/>
										<UML:TaggedValue tag="tpos" value="0"/>
										<UML:TaggedValue tag="ea_localid" value="20"/>
										<UML:TaggedValue tag="ea_eleType" value="package"/>
										<UML:TaggedValue tag="style" value="BackColor=-1;BorderColor=-1;BorderWidth=-1;FontColor=-1;VSwimLanes=1;HSwimLanes=1;BorderStyle=0;"/>
									</UML:ModelElement.taggedValue>
								</UML:ClassifierRole>
								<UML:ClassifierRole name="03 Modelo de Dominio" xmi.id="EAID_B4DB7B95_8E65_4a97_A02A_5B47BFBD78C5" visibility="public" base="EAID_11111111_5487_4080_A7F4_41526CB0AA00">
									<UML:ModelElement.taggedValue>
										<UML:TaggedValue tag="isAbstract" value="false"/>
										<UML:TaggedValue tag="isSpecification" value="false"/>
										<UML:TaggedValue tag="ea_stype" value="Package"/>
										<UML:TaggedValue tag="ea_ntype" value="0"/>
										<UML:TaggedValue tag="isActive" value="false"/>
										<UML:TaggedValue tag="package" value="EAPK_EEA186C1_50AD_43fe_84BC_7272F4234FCD"/>
										<UML:TaggedValue tag="date_created" value="2015-08-19 15:59:14"/>
										<UML:TaggedValue tag="date_modified" value="2015-08-19 16:03:23"/>
										<UML:TaggedValue tag="tagged" value="0"/>
										<UML:TaggedValue tag="package2" value="EAID_B4DB7B95_8E65_4a97_A02A_5B47BFBD78C5"/>
										<UML:TaggedValue tag="package_name" value="Dictamen"/>
										<UML:TaggedValue tag="phase" value="1.0"/>
										<UML:TaggedValue tag="complexity" value="1"/>
										<UML:TaggedValue tag="status" value="Proposed"/>
										<UML:TaggedValue tag="tpos" value="6"/>
										<UML:TaggedValue tag="ea_localid" value="23"/>
										<UML:TaggedValue tag="ea_eleType" value="package"/>
										<UML:TaggedValue tag="style" value="BackColor=-1;BorderColor=-1;BorderWidth=-1;FontColor=-1;VSwimLanes=1;HSwimLanes=1;BorderStyle=0;"/>
									</UML:ModelElement.taggedValue>
								</UML:ClassifierRole>
							</UML:Namespace.ownedElement>
							<UML:Collaboration.interaction/>
						</UML:Collaboration>
						<UML:Package name="01 Modelo de Procesos" xmi.id="EAPK_9D49D945_9AF5_4ecb_A561_AB014F6E260C" isRoot="false" isLeaf="false" isAbstract="false" visibility="public">
							<UML:ModelElement.taggedValue>
								<UML:TaggedValue tag="parent" value="EAPK_EEA186C1_50AD_43fe_84BC_7272F4234FCD"/>
								<UML:TaggedValue tag="created" value="2011-03-24 00:00:00"/>
								<UML:TaggedValue tag="modified" value="2015-08-19 16:03:02"/>
								<UML:TaggedValue tag="iscontrolled" value="TRUE"/>
								<UML:TaggedValue tag="xmlpath" value="ModeloProcesos\01 Modelo de Procesos.xml"/>
								<UML:TaggedValue tag="lastloaddate" value="2015-08-19 15:58:55"/>
								<UML:TaggedValue tag="lastsavedate" value="2011-05-12 13:30:18"/>
								<UML:TaggedValue tag="version" value="1.0"/>
								<UML:TaggedValue tag="isprotected" value="FALSE"/>
								<UML:TaggedValue tag="usedtd" value="FALSE"/>
								<UML:TaggedValue tag="owner" value="ajfuentes"/>
								<UML:TaggedValue tag="xmiver" value="Enterprise Architect XMI/UML 1.3"/>
								<UML:TaggedValue tag="logxml" value="FALSE"/>
								<UML:TaggedValue tag="tpos" value="0"/>
								<UML:TaggedValue tag="batchsave" value="0"/>
								<UML:TaggedValue tag="batchload" value="0"/>
								<UML:TaggedValue tag="packageFlags" value="isModel=1;Recurse=0;VCCFG=Dictamen;"/>
								<UML:TaggedValue tag="savedasstub" value="true"/>
								<UML:TaggedValue tag="phase" value="1.0"/>
								<UML:TaggedValue tag="status" value="Proposed"/>
								<UML:TaggedValue tag="complexity" value="1"/>
								<UML:TaggedValue tag="ea_stype" value="Public"/>
							</UML:ModelElement.taggedValue>
						</UML:Package>
						<UML:Package name="03 Modelo de Requerimientos" xmi.id="EAPK_7774EFC6_D830_40a8_83A5_256C6BF2B95E" isRoot="false" isLeaf="false" isAbstract="false" visibility="public">
							<UML:ModelElement.taggedValue>
								<UML:TaggedValue tag="parent" value="EAPK_EEA186C1_50AD_43fe_84BC_7272F4234FCD"/>
								<UML:TaggedValue tag="created" value="2005-11-19 09:02:21"/>
								<UML:TaggedValue tag="modified" value="2015-08-19 16:07:59"/>
								<UML:TaggedValue tag="iscontrolled" value="TRUE"/>
								<UML:TaggedValue tag="xmlpath" value="ModeloRequerimientos\03 Modelo de Requerimientos.xml"/>
								<UML:TaggedValue tag="lastloaddate" value="2005-11-19 09:02:21"/>
								<UML:TaggedValue tag="lastsavedate" value="2005-11-19 09:26:01"/>
								<UML:TaggedValue tag="isprotected" value="FALSE"/>
								<UML:TaggedValue tag="usedtd" value="FALSE"/>
								<UML:TaggedValue tag="owner" value="ajfuentes"/>
								<UML:TaggedValue tag="xmiver" value="Enterprise Architect XMI/UML 1.3"/>
								<UML:TaggedValue tag="logxml" value="FALSE"/>
								<UML:TaggedValue tag="tpos" value="2"/>
								<UML:TaggedValue tag="batchsave" value="0"/>
								<UML:TaggedValue tag="batchload" value="0"/>
								<UML:TaggedValue tag="packageFlags" value="isModel=1;Recurse=0;VCCFG=Dictamen;"/>
								<UML:TaggedValue tag="savedasstub" value="true"/>
								<UML:TaggedValue tag="phase" value="1.0"/>
								<UML:TaggedValue tag="status" value="Proposed"/>
								<UML:TaggedValue tag="complexity" value="1"/>
								<UML:TaggedValue tag="ea_stype" value="Public"/>
							</UML:ModelElement.taggedValue>
						</UML:Package>
						<UML:Package name="02 Modelo Funcional" xmi.id="EAPK_637A3138_D9F0_49ea_A177_EC26F6D73622" isRoot="false" isLeaf="false" isAbstract="false" visibility="public">
							<UML:ModelElement.taggedValue>
								<UML:TaggedValue tag="parent" value="EAPK_EEA186C1_50AD_43fe_84BC_7272F4234FCD"/>
								<UML:TaggedValue tag="created" value="2015-08-19 15:57:05"/>
								<UML:TaggedValue tag="modified" value="2015-08-19 16:08:20"/>
								<UML:TaggedValue tag="iscontrolled" value="TRUE"/>
								<UML:TaggedValue tag="xmlpath" value="ModeloFuncional\02 Modelo Funcional.xml"/>
								<UML:TaggedValue tag="lastloaddate" value="2015-08-19 15:57:11"/>
								<UML:TaggedValue tag="lastsavedate" value="2015-08-19 15:57:05"/>
								<UML:TaggedValue tag="isprotected" value="FALSE"/>
								<UML:TaggedValue tag="usedtd" value="FALSE"/>
								<UML:TaggedValue tag="owner" value="ajfuentes"/>
								<UML:TaggedValue tag="xmiver" value="Enterprise Architect XMI/UML 1.3"/>
								<UML:TaggedValue tag="logxml" value="FALSE"/>
								<UML:TaggedValue tag="tpos" value="3"/>
								<UML:TaggedValue tag="batchsave" value="0"/>
								<UML:TaggedValue tag="batchload" value="0"/>
								<UML:TaggedValue tag="packageFlags" value="isModel=1;VICON=1;Recurse=0;VCCFG=Dictamen;"/>
								<UML:TaggedValue tag="savedasstub" value="true"/>
								<UML:TaggedValue tag="phase" value="1.0"/>
								<UML:TaggedValue tag="status" value="Proposed"/>
								<UML:TaggedValue tag="complexity" value="1"/>
								<UML:TaggedValue tag="ea_stype" value="Public"/>
							</UML:ModelElement.taggedValue>
						</UML:Package>
						<UML:Package name="03 Modelo de Dominio" xmi.id="EAPK_B4DB7B95_8E65_4a97_A02A_5B47BFBD78C5" isRoot="false" isLeaf="false" isAbstract="false" visibility="public">
							<UML:ModelElement.taggedValue>
								<UML:TaggedValue tag="parent" value="EAPK_EEA186C1_50AD_43fe_84BC_7272F4234FCD"/>
								<UML:TaggedValue tag="created" value="2015-08-19 15:59:14"/>
								<UML:TaggedValue tag="modified" value="2015-08-19 16:03:23"/>
								<UML:TaggedValue tag="iscontrolled" value="TRUE"/>
								<UML:TaggedValue tag="isnamespace" value="1"/>
								<UML:TaggedValue tag="xmlpath" value="ModeloDominio\03 Modelo de Dominio.xml"/>
								<UML:TaggedValue tag="lastloaddate" value="2015-08-19 15:59:14"/>
								<UML:TaggedValue tag="lastsavedate" value="2015-08-19 15:59:14"/>
								<UML:TaggedValue tag="isprotected" value="FALSE"/>
								<UML:TaggedValue tag="usedtd" value="FALSE"/>
								<UML:TaggedValue tag="owner" value="ajfuentes"/>
								<UML:TaggedValue tag="xmiver" value="Enterprise Architect XMI/UML 1.3"/>
								<UML:TaggedValue tag="logxml" value="FALSE"/>
								<UML:TaggedValue tag="tpos" value="6"/>
								<UML:TaggedValue tag="batchsave" value="0"/>
								<UML:TaggedValue tag="batchload" value="0"/>
								<UML:TaggedValue tag="packageFlags" value="isModel=1;VICON=3;Recurse=0;VCCFG=Dictamen;"/>
								<UML:TaggedValue tag="savedasstub" value="true"/>
								<UML:TaggedValue tag="phase" value="1.0"/>
								<UML:TaggedValue tag="status" value="Proposed"/>
								<UML:TaggedValue tag="complexity" value="1"/>
								<UML:TaggedValue tag="ea_stype" value="Public"/>
							</UML:ModelElement.taggedValue>
						</UML:Package>
						<UML:Package name="04 Diseño Tecnico" xmi.id="EAPK_18FE430E_5F97_4cf9_BDAD_279FA43C2A8B" isRoot="false" isLeaf="false" isAbstract="false" visibility="public">
							<UML:ModelElement.taggedValue>
								<UML:TaggedValue tag="parent" value="EAPK_EEA186C1_50AD_43fe_84BC_7272F4234FCD"/>
								<UML:TaggedValue tag="created" value="2015-08-19 15:57:27"/>
								<UML:TaggedValue tag="modified" value="2015-08-19 16:03:28"/>
								<UML:TaggedValue tag="iscontrolled" value="TRUE"/>
								<UML:TaggedValue tag="xmlpath" value="DisenoTecnico\04 Diseño Tecnico.xml"/>
								<UML:TaggedValue tag="lastloaddate" value="2015-08-19 15:57:27"/>
								<UML:TaggedValue tag="lastsavedate" value="2015-08-19 15:57:27"/>
								<UML:TaggedValue tag="isprotected" value="FALSE"/>
								<UML:TaggedValue tag="usedtd" value="FALSE"/>
								<UML:TaggedValue tag="owner" value="ajfuentes"/>
								<UML:TaggedValue tag="xmiver" value="Enterprise Architect XMI/UML 1.3"/>
								<UML:TaggedValue tag="logxml" value="FALSE"/>
								<UML:TaggedValue tag="tpos" value="7"/>
								<UML:TaggedValue tag="batchsave" value="0"/>
								<UML:TaggedValue tag="batchload" value="0"/>
								<UML:TaggedValue tag="packageFlags" value="isModel=1;VICON=4;Recurse=0;VCCFG=Dictamen;"/>
								<UML:TaggedValue tag="savedasstub" value="true"/>
								<UML:TaggedValue tag="phase" value="1.0"/>
								<UML:TaggedValue tag="status" value="Proposed"/>
								<UML:TaggedValue tag="complexity" value="1"/>
								<UML:TaggedValue tag="ea_stype" value="Public"/>
							</UML:ModelElement.taggedValue>
						</UML:Package>
					</UML:Namespace.ownedElement>
				</UML:Package>
			</UML:Namespace.ownedElement>
		</UML:Model>
	</XMI.content>
	<XMI.difference/>
	<XMI.extensions xmi.extender="Enterprise Architect 2.5"/>
</XMI>
